{"description":"Assert various searches and data in WebTable|Assert WebTable Section","passed":true,"pending":false,"os":"Windows","instanceId":15244,"browser":{"name":"chrome","version":"89.0.4389.114"},"message":"Passed.","trace":"","browserLogs":[{"level":"SEVERE","message":"https://pagead2.googlesyndication.com/pagead/js/adsbygoogle.js 219:117 Uncaught P: adsbygoogle.push() error: Only one 'enable_page_level_ads' allowed per page.","timestamp":1618382536959,"type":""}],"screenShotFile":"images\\008b005c-0074-00c5-008b-001a00310042.png","timestamp":1618382536770,"duration":4373}
