{"description":"Assert all courses by searching protractor|Assert Course selection","passed":true,"pending":false,"os":"Windows","instanceId":3472,"browser":{"name":"chrome","version":"90.0.4430.72"},"message":"Passed","browserLogs":[{"level":"SEVERE","message":"https://www.selenium-tutorial.com/ahoy/events - Failed to load resource: the server responded with a status of 403 ()","timestamp":1618811881960,"type":""},{"level":"SEVERE","message":"https://www.selenium-tutorial.com/ahoy/events - Failed to load resource: the server responded with a status of 403 ()","timestamp":1618811881983,"type":""},{"level":"SEVERE","message":"https://www.selenium-tutorial.com/ahoy/events - Failed to load resource: the server responded with a status of 403 ()","timestamp":1618811882001,"type":""},{"level":"SEVERE","message":"https://www.selenium-tutorial.com/ahoy/events - Failed to load resource: the server responded with a status of 403 ()","timestamp":1618811882147,"type":""},{"level":"SEVERE","message":"https://www.selenium-tutorial.com/ahoy/events - Failed to load resource: the server responded with a status of 403 ()","timestamp":1618811882148,"type":""},{"level":"SEVERE","message":"https://www.selenium-tutorial.com/ahoy/events - Failed to load resource: the server responded with a status of 403 ()","timestamp":1618811882149,"type":""},{"level":"SEVERE","message":"https://www.selenium-tutorial.com/ahoy/events - Failed to load resource: the server responded with a status of 403 ()","timestamp":1618811883049,"type":""},{"level":"SEVERE","message":"https://www.selenium-tutorial.com/ahoy/events - Failed to load resource: the server responded with a status of 403 ()","timestamp":1618811888913,"type":""},{"level":"SEVERE","message":"https://www.selenium-tutorial.com/ahoy/events - Failed to load resource: the server responded with a status of 403 ()","timestamp":1618811894001,"type":""},{"level":"SEVERE","message":"https://www.selenium-tutorial.com/ahoy/events - Failed to load resource: the server responded with a status of 403 ()","timestamp":1618811900976,"type":""},{"level":"SEVERE","message":"https://www.selenium-tutorial.com/ahoy/events - Failed to load resource: the server responded with a status of 403 ()","timestamp":1618811906066,"type":""},{"level":"SEVERE","message":"https://www.selenium-tutorial.com/ahoy/events - Failed to load resource: the server responded with a status of 403 ()","timestamp":1618811911154,"type":""},{"level":"SEVERE","message":"https://www.selenium-tutorial.com/ahoy/events - Failed to load resource: the server responded with a status of 403 ()","timestamp":1618811916425,"type":""}],"screenShotFile":"images\\00f3003c-00fc-00d7-00c9-003d003d009a.png","timestamp":1618811880550,"duration":35869}
